hashbrown/_DataH.py
hashbrown/_FunctionBasic.py
hashbrown/_HashBrown.py
hashbrown/__init__.py
hashbrown-4.4.1.dist-info/LICENSE.md
hashbrown-4.4.1.dist-info/METADATA
hashbrown-4.4.1.dist-info/WHEEL
hashbrown-4.4.1.dist-info/top_level.txt
hashbrown-4.4.1.dist-info/RECORD
