Metadata-Version: 2.1
Name: hashbrown
Version: 4.4.1
Summary: A Python library for Runge-Kutta 4th order solver and interpreter. Designed for students in KSA.
Home-page: https://github.com/iamchoking/Hashbrown
Author: Hyungho Chris Choi
Author-email: iamchoking247@gmail.com
License: MIT
Platform: UNKNOWN
Classifier: Programming Language :: Python :: 3
Classifier: Programming Language :: Python :: 3.5
Classifier: Programming Language :: Python :: 3.7
Requires-Dist: openpyxl
Requires-Dist: matplotlib
Requires-Dist: numpy
